LICENSE
MANIFEST.in
README.md
setup.py
blobstash/docstore/__init__.py
blobstash/docstore/attachment.py
blobstash/docstore/error.py
blobstash/docstore/query.py
blobstash_docstore.egg-info/PKG-INFO
blobstash_docstore.egg-info/SOURCES.txt
blobstash_docstore.egg-info/dependency_links.txt
blobstash_docstore.egg-info/requires.txt
blobstash_docstore.egg-info/top_level.txt