Metadata-Version: 1.2
Name: blobstash-docstore
Version: 0.0.6
Summary: BlobStash DocStore client
Home-page: https://github.com/tsileo/blobstash-python-docstore
Author: Thomas Sileo
Author-email: t@a4.io
License: MIT
Keywords: blobstash DocStore client JSON Lua document store
Platform: UNKNOWN
Classifier: Development Status :: 3 - Alpha
Classifier: Intended Audience :: Developers
Classifier: License :: OSI Approved :: MIT License
Classifier: Programming Language :: Python :: 3
Classifier: Programming Language :: Python :: 3.6
Requires-Python: >=3.6
